djsce/__init__.py
djsce/ai.py
djsce/daa.py
djsce/de.py
djsce/dsa.py
djsce/os.py
djsce/poa.py
djsce/python.py
djsce-0.2.3.dist-info/LICENSE
djsce-0.2.3.dist-info/METADATA
djsce-0.2.3.dist-info/WHEEL
djsce-0.2.3.dist-info/top_level.txt
djsce-0.2.3.dist-info/RECORD
