Metadata-Version: 2.1
Name: djsce
Version: 0.2.3
Summary: DJSCE
Home-page: 
Author: Mihir Panchal
Author-email: mihirpanchal5400@gmail.com
License: MIT
Keywords: djsce
Classifier: Development Status :: 5 - Production/Stable
Classifier: Intended Audience :: Education
Classifier: Operating System :: Microsoft :: Windows :: Windows 10
Classifier: License :: OSI Approved :: MIT License
Classifier: Programming Language :: Python :: 3
License-File: LICENSE
